v2v/__init__.py
v2v/_audio_extractor_.py
v2v/_audio_merger_.py
v2v/_const_.py
v2v/_frame_organizer_.py
v2v/_image2video_processor_.py
v2v/_null_frame_processor_.py
v2v/_null_frame_processor_pool_.py
v2v/_video2image_processor_.py
v2v/_video2video_processor_.py
v2v/datastruct/__init__.py
v2v/datastruct/_frame_data_.py
v2v/datastruct/_progress_.py
v2v/datastruct/_video_info_.py
v2v/interface/__init__.py
v2v/interface/_i_frame_processor_.py
v2v/interface/_i_frame_processor_manager_.py
v2v/utils/__init__.py
v2v/utils/_uuid_.py
v2v/utils/_video_utils_.py
v2v-1.2.4.dist-info/LICENSE
v2v-1.2.4.dist-info/METADATA
v2v-1.2.4.dist-info/WHEEL
v2v-1.2.4.dist-info/top_level.txt
v2v-1.2.4.dist-info/RECORD
