Metadata-Version: 2.1
Name: v2v
Version: 1.2.4
Summary: # Video2Video
Author-email: 404Vector <tiryul@gmail.com>
License: MIT License
Project-URL: Home, https://github.com/404Vector/Video2Video
Classifier: License :: OSI Approved :: MIT License
Requires-Python: >=3.9
License-File: LICENSE
Requires-Dist: setuptools
Requires-Dist: ffmpeg-python
Requires-Dist: numpy
